scipyx/__init__.py
scipyx/_ellip.py
scipyx/_interpolation.py
scipyx/_krylov.py
scipyx/_nonlinear.py
scipyx/_optimize.py
scipyx-0.0.18.dist-info/LICENSE
scipyx-0.0.18.dist-info/METADATA
scipyx-0.0.18.dist-info/WHEEL
scipyx-0.0.18.dist-info/top_level.txt
scipyx-0.0.18.dist-info/RECORD
