Metadata-Version: 2.1
Name: scipyx
Version: 0.0.18
Summary: SciPy fixes and extensions
Home-page: https://github.com/nschloe/scipyx
Author: Nico Schlömer
Author-email: nico.schloemer@gmail.com
License: BSD-3-Clause
Project-URL: Code, https://github.com/nschloe/scipyx
Project-URL: Issues, https://github.com/nschloe/scipyx/issues
Project-URL: Funding, https://github.com/sponsors/nschloe
Platform: UNKNOWN
Classifier: Development Status :: 4 - Beta
Classifier: Intended Audience :: Science/Research
Classifier: License :: OSI Approved :: BSD License
Classifier: Operating System :: OS Independent
Classifier: Programming Language :: Python
Classifier: Programming Language :: Python :: 3
Classifier: Programming Language :: Python :: 3.7
Classifier: Programming Language :: Python :: 3.8
Classifier: Programming Language :: Python :: 3.9
Classifier: Programming Language :: Python :: 3.10
Classifier: Topic :: Scientific/Engineering
Classifier: Topic :: Utilities
Requires-Python: >=3.7
License-File: LICENSE
Requires-Dist: numpy (>=1.20.0)
Requires-Dist: scipy
